dspMetadataGUI/__init__.py
dspMetadataGUI/collectMetadata.py
dspMetadataGUI/util/__init__.py
dspMetadataGUI/util/converter.py
dspMetadataGUI/util/dataHandling.py
dspMetadataGUI/util/metaDataSet.py
dspMetadataGUI/util/rdfConverter.py
dspMetadataGUI/util/utils.py
test/__init__.py
test/test_utils.py
dsp_metadata_gui-8.5.0.dist-info/LICENSE
dsp_metadata_gui-8.5.0.dist-info/METADATA
dsp_metadata_gui-8.5.0.dist-info/WHEEL
dsp_metadata_gui-8.5.0.dist-info/entry_points.txt
dsp_metadata_gui-8.5.0.dist-info/top_level.txt
dsp_metadata_gui-8.5.0.dist-info/RECORD
