Metadata-Version: 2.1
Name: dsp-metadata-gui
Version: 8.5.0
Summary: Python GUI tool to collect metadata for DSP projects.
Home-page: https://github.com/dasch-swiss/dsp-metadata-gui
Author: Balduin Landolt
Author-email: balduin.landolt@dasch.swiss
License: GPLv3
Classifier: Programming Language :: Python :: 3
Classifier: License :: OSI Approved :: GNU General Public License v3 (GPLv3)
Classifier: Operating System :: OS Independent
Requires-Python: >=3.10.0
License-File: LICENSE
Requires-Dist: beautifulsoup4 ==4.11.2
Requires-Dist: charset-normalizer ==3.0.1
Requires-Dist: guess-language-spirit ==0.5.3
Requires-Dist: isodate ==0.6.1
Requires-Dist: jsonschema ==4.17.3
Requires-Dist: langdetect ==1.0.9
Requires-Dist: langid ==1.1.6
Requires-Dist: owlrl ==6.0.2
Requires-Dist: pyenchant ==3.2.2
Requires-Dist: pyshacl ==0.20.0
Requires-Dist: requests ==2.28.2
Requires-Dist: textblob ==0.17.1
Requires-Dist: validators ==0.20.0
Requires-Dist: wcwidth ==0.2.6
Requires-Dist: webencodings ==0.5.1
Requires-Dist: wxpython ==4.2.0
Requires-Dist: pyparsing ==3.0.9 ; python_full_version >= "3.6.8"
Requires-Dist: six ==1.16.0 ; python_version >= "2.7" and python_version not in "3.0, 3.1, 3.2, 3.3"
Requires-Dist: tqdm ==4.64.1 ; python_version >= "2.7" and python_version not in "3.0, 3.1, 3.2, 3.3"
Requires-Dist: html5lib ==1.1 ; python_version >= "2.7" and python_version not in "3.0, 3.1, 3.2, 3.3, 3.4"
Requires-Dist: urllib3 ==1.26.14 ; python_version >= "2.7" and python_version not in "3.0, 3.1, 3.2, 3.3, 3.4, 3.5"
Requires-Dist: nltk ==3.8.1 ; python_version >= "3"
Requires-Dist: decorator ==5.1.1 ; python_version >= "3.5"
Requires-Dist: idna ==3.4 ; python_version >= "3.5"
Requires-Dist: attrs ==22.2.0 ; python_version >= "3.6"
Requires-Dist: certifi ==2022.12.7 ; python_version >= "3.6"
Requires-Dist: prettytable ==2.5.0 ; python_version >= "3.6"
Requires-Dist: regex ==2022.10.31 ; python_version >= "3.6"
Requires-Dist: soupsieve ==2.3.2.post1 ; python_version >= "3.6"
Requires-Dist: click ==8.1.3 ; python_version >= "3.7"
Requires-Dist: joblib ==1.2.0 ; python_version >= "3.7"
Requires-Dist: packaging ==23.0 ; python_version >= "3.7"
Requires-Dist: pillow ==9.4.0 ; python_version >= "3.7"
Requires-Dist: pyrsistent ==0.19.3 ; python_version >= "3.7"
Requires-Dist: rdflib ==6.2.0 ; python_version >= "3.7"
Requires-Dist: setuptools ==67.3.1 ; python_version >= "3.7"
Requires-Dist: numpy ==1.24.2 ; python_version >= "3.8"
